Workbook
Name anos: Spinvest!$D$20
Name aporte: Spinvest!$D$19
Name aporte2: Spinvest!$C$33
Name dividendos: Spinvest!$D$23
Name patrimonio: Spinvest!$D$22
Name rendimento_carteira: Spinvest!$D$15
Name salario: Spinvest!$B$14
Name sugestaodeaporte: Spinvest!$D$16
Name taxamensal: Spinvest!$D$21
Name valor_futuro: Spinvest!$D$22
Name Vencimento: Spinvest!$D$14

Sheet Spinvest
B13: Configurações
B14: Salário | D14: 30000
B15: Rendimento da Carteira | D15: 0.007
B16: Sugestão de Investimento | D16: =Vencimento*30% -> 9000
B18: Investimento Mensal
B19: Quanto Investir por mês? | D19: 5000
B20: Por Quantos Anos? | D20: 5
B21: Taxa de Rendimento Mensal | D21: 0.01079
B22: Patrimônio Acumulado | D22: =FV(taxamensal,anos*12,(aporte*-1),0,0) -> 418884.57
B23: Dividendos Mensais | D23: =patrimonio*rendimento_carteira -> 2932.192
B25: Cenários | D25: Dividendos
A26: 2 | B26: Quanto em 2 anos? | C26: =FV($D$21,$A26*12,-$D$19,0,0) -> 136138.14 | D26: =C26*rendimento_carteira -> 952.96696
A27: 5 | B27: Quanto em 5 anos? | C27: =FV($D$21,$A27*12,-$D$19,0,0) -> 418884.57 | D27: =C27*rendimento_carteira -> 2932.192
A28: 10 | B28: Quanto em 10 anos? | C28: =FV($D$21,$A28*12,-$D$19,0,0) -> 1216421.1 | D28: =C28*rendimento_carteira -> 8514.9474
A29: 20 | B29: Quanto em 20 anos? | C29: =FV($D$21,$A29*12,-$D$19,0,0) -> 5625992 | D29: =C29*rendimento_carteira -> 39381.944
A30: 30 | B30: Quanto em 25 anos? | C30: =FV($D$21,$A30*12,-$D$19,0,0) -> 21610848 | D30: =C30*rendimento_carteira -> 151275.94
B32: Perfis | C32: Conservador
B33: Valor a Ser Investido Mensal | C33: =aporte -> 5000
B35: Tipo de FII | C35: Percentual Sugerido | D35: Valor
B36: Papel | C36: =VLOOKUP($C$32&"-"&$B36,Planilha2!$A$3:$D$20,4,0) -> 0.3 | D36: =aporte2*C36 -> 1500
B37: Tijolo | C37: =VLOOKUP($C$32&"-"&$B37,Planilha2!$A$3:$D$20,4,0) -> 0.4 | D37: =aporte2*C37 -> 2000
B38: Híbrido | C38: =VLOOKUP($C$32&"-"&$B38,Planilha2!$A$3:$D$20,4,0) -> 0.1 | D38: =aporte2*C38 -> 500
B39: FOFs | C39: =VLOOKUP($C$32&"-"&$B39,Planilha2!$A$3:$D$20,4,0) -> 0.1 | D39: =aporte2*C39 -> 500
B40: Desenvolvimento | C40: =VLOOKUP($C$32&"-"&$B40,Planilha2!$A$3:$D$20,4,0) -> 0.05 | D40: =aporte2*C40 -> 250
B41: Hotelaria | C41: =VLOOKUP($C$32&"-"&$B41,Planilha2!$A$3:$D$20,4,0) -> 0.05 | D41: =aporte2*C41 -> 250
D42: =SUM(D36:D41) -> 5000

Sheet Planilha2
A2: Chave | B2: Perfil | C2: Tipo de FII | D2: Margem
A3: =B3&"-"&C3 -> Conservador-Papel | B3: Conservador | C3: Papel | D3: 0.3
A4: =B4&"-"&C4 -> Conservador-Tijolo | B4: Conservador | C4: Tijolo | D4: 0.4
A5: =B5&"-"&C5 -> Conservador-Híbrido | B5: Conservador | C5: Híbrido | D5: 0.1
A6: =B6&"-"&C6 -> Conservador-FOFs | B6: Conservador | C6: FOFs | D6: 0.1
A7: =B7&"-"&C7 -> Conservador-Desenvolvimento | B7: Conservador | C7: Desenvolvimento | D7: 0.05
A8: =B8&"-"&C8 -> Conservador-Hotelaria | B8: Conservador | C8: Hotelaria | D8: 0.05
A9: =B9&"-"&C9 -> Moderado-Papel | B9: Moderado | C9: Papel | D9: 0.32
A10: =B10&"-"&C10 -> Moderado-Tijolo | B10: Moderado | C10: Tijolo | D10: 0.3
A11: =B11&"-"&C11 -> Moderado-Híbrido | B11: Moderado | C11: Híbrido | D11: 0.08
A12: =B12&"-"&C12 -> Moderado-FOFs | B12: Moderado | C12: FOFs | D12: 0.1
A13: =B13&"-"&C13 -> Moderado-Desenvolvimento | B13: Moderado | C13: Desenvolvimento | D13: 0.1
A14: =B14&"-"&C14 -> Moderado-Hotelaria | B14: Moderado | C14: Hotelaria | D14: 0.1
... A20: =B20&"-"&C20 -> Agressivo-Hotelaria | B20: Agressivo | C20: Hotelaria | D20: 0.1
